odoo/addons/mrp_lot_production_date/README.rst
odoo/addons/mrp_lot_production_date/__init__.py
odoo/addons/mrp_lot_production_date/__manifest__.py
odoo/addons/mrp_lot_production_date/i18n/it.po
odoo/addons/mrp_lot_production_date/i18n/mrp_lot_production_date.pot
odoo/addons/mrp_lot_production_date/i18n/pt_BR.po
odoo/addons/mrp_lot_production_date/models/__init__.py
odoo/addons/mrp_lot_production_date/models/mrp_production.py
odoo/addons/mrp_lot_production_date/readme/CONTRIBUTORS.md
odoo/addons/mrp_lot_production_date/readme/CREDITS.md
odoo/addons/mrp_lot_production_date/readme/DESCRIPTION.md
odoo/addons/mrp_lot_production_date/readme/USAGE.md
odoo/addons/mrp_lot_production_date/static/description/icon.png
odoo/addons/mrp_lot_production_date/static/description/index.html
odoo/addons/mrp_lot_production_date/tests/__init__.py
odoo/addons/mrp_lot_production_date/tests/test_production_date.py
odoo_addon_mrp_lot_production_date-18.0.1.0.0.3.dist-info/METADATA
odoo_addon_mrp_lot_production_date-18.0.1.0.0.3.dist-info/WHEEL
odoo_addon_mrp_lot_production_date-18.0.1.0.0.3.dist-info/top_level.txt
odoo_addon_mrp_lot_production_date-18.0.1.0.0.3.dist-info/RECORD
